cmfn/__about__.py
cmfn/__init__.py
cmfn/jsonl.py
cmfn-0.0.6.dist-info/METADATA
cmfn-0.0.6.dist-info/WHEEL
cmfn-0.0.6.dist-info/RECORD
