Metadata-Version: 2.3
Name: cmfn
Version: 0.0.6
Project-URL: Documentation, https://github.com/dataset-sh/cmfn#readme
Project-URL: Issues, https://github.com/dataset-sh/cmfn/issues
Project-URL: Source, https://github.com/dataset-sh/cmfn
Author-email: Hao Wu <haowu@dataset.sh>
License: MIT
Classifier: Development Status :: 4 - Beta
Classifier: Programming Language :: Python
Classifier: Programming Language :: Python :: 3.8
Classifier: Programming Language :: Python :: 3.9
Classifier: Programming Language :: Python :: 3.10
Classifier: Programming Language :: Python :: 3.11
Classifier: Programming Language :: Python :: 3.12
Classifier: Programming Language :: Python :: Implementation :: CPython
Classifier: Programming Language :: Python :: Implementation :: PyPy
Requires-Python: >=3.8
